[{"_id":2,"mountain_id":"0","firstName":"Ana","lastName":"Lijeskic","dateFrom":{"year":2022,"month":4,"day":4},"dateTo":{"year":2022,"month":4,"day":6},"price":"5990"},{"_id":3,"mountain_id":"0","firstName":"Ana","lastName":"Lijeskic","dateFrom":{"year":2022,"month":4,"day":4},"dateTo":{"year":2022,"month":4,"day":6},"price":"5990"},{"_id":4,"mountain_id":"0","firstName":"Ana","lastName":"Lijeskic","dateFrom":{"year":2022,"month":4,"day":4},"dateTo":{"year":2022,"month":4,"day":6},"price":"5990"},{"_id":5,"mountain_id":"0","firstName":"","lastName":"","dateFrom":{"year":2022,"month":4,"day":1},"dateTo":{"year":2022,"month":4,"day":3},"price":"5990"}]